tensor_disentangler/__init__.py
tensor_disentangler/disentangle.py
tensor_disentangler-0.0.1.dist-info/METADATA
tensor_disentangler-0.0.1.dist-info/WHEEL
tensor_disentangler-0.0.1.dist-info/licenses/LICENSE
tensor_disentangler-0.0.1.dist-info/RECORD
