Metadata-Version: 2.4
Name: tensor_disentangler
Version: 0.0.1
Summary: Numerical optimization of tensor network disentanglers
Project-URL: Homepage, https://github.com/adektor/tensor-disentangle
Project-URL: Issues, https://github.com/adektor/tensor-disentangler/issues
Author-email: Alec Dektor <alec.dektor@gmail.com>
License-Expression: MIT
License-File: LICENSE
Classifier: Operating System :: OS Independent
Classifier: Programming Language :: Python :: 3
Requires-Python: >=3.9
Requires-Dist: matplotlib>=3.0
Requires-Dist: numpy>=1.13.0
Requires-Dist: pymanopt>=2.2.1
